Metadata-Version: 2.1
Name: terra-pandas
Version: 0.0.1
Summary: Tools work with Terra data tables in Pandas
Home-page: https://github.com/xbrianh/terra-pandas.git
Author: Brian Hannafious
Author-email: bhannafi@ucsc.edu
License: MIT
Platform: MacOS X
Platform: Posix
Classifier: Intended Audience :: Developers
Classifier: License :: OSI Approved :: MIT License
Classifier: Programming Language :: Python :: 3.7
